dez/__init__.py
dez/bench.py
dez/buffer.py
dez/io.py
dez/logging.py
dez/memcache.py
dez/version.py
dez/xml_tools.py
dez/http/__init__.py
dez/http/application.py
dez/http/cache.py
dez/http/counter.py
dez/http/errors.py
dez/http/fetch.py
dez/http/inotify.py
dez/http/reverseproxy.py
dez/http/static.py
dez/http/wsgithreadpool.py
dez/http/client/__init__.py
dez/http/client/client.py
dez/http/client/request.py
dez/http/client/response.py
dez/http/proxy/__init__.py
dez/http/proxy/proxy.py
dez/http/server/__init__.py
dez/http/server/request.py
dez/http/server/response.py
dez/http/server/router.py
dez/http/server/server.py
dez/http/server/shield.py
dez/network/__init__.py
dez/network/client.py
dez/network/connection.py
dez/network/controller.py
dez/network/server.py
dez/network/websocket.py
dez/op/__init__.py
dez/op/server/__init__.py
dez/op/server/connection.py
dez/op/server/frame.py
dez/op/server/server.py
dez/op/server/validator.py
dez/samples/__init__.py
dez/samples/app_proxy.py
dez/samples/django_hello_world.py
dez/samples/echo_server.py
dez/samples/get_url.py
dez/samples/hello_client.py
dez/samples/http_client.py
dez/samples/http_client2.py
dez/samples/http_load_test.py
dez/samples/http_proxy.py
dez/samples/httpd_hello_world.py
dez/samples/new_conn.py
dez/samples/op_callback_server.py
dez/samples/op_callback_test.py
dez/samples/op_test.py
dez/samples/stomp_test.py
dez/samples/test.py
dez/samples/websocket_proxy_test.py
dez/samples/websocket_test.py
dez/samples/wsc.py
dez/samples/wsecho.py
dez/samples/wsgi_test.py
dez/stomp/__init__.py
dez/stomp/server/__init__.py
dez/stomp/server/frame.py
dez/stomp/server/server.py
dez/stomp/server/validator.py
dez-0.10.10.45.dist-info/LICENSE
dez-0.10.10.45.dist-info/METADATA
dez-0.10.10.45.dist-info/WHEEL
dez-0.10.10.45.dist-info/entry_points.txt
dez-0.10.10.45.dist-info/top_level.txt
dez-0.10.10.45.dist-info/RECORD
