Metadata-Version: 2.1
Name: dez
Version: 0.10.10.45
Summary: A set of pyevent-based network services
Author: Mario Balibrera
Author-email: mario.balibrera@gmail.com
License: MIT License
Classifier: Development Status :: 5 - Production/Stable
Classifier: Environment :: Console
Classifier: Intended Audience :: Developers
Classifier: License :: OSI Approved :: MIT License
Classifier: Operating System :: OS Independent
Classifier: Programming Language :: Python
Classifier: Topic :: Software Development :: Libraries :: Python Modules
License-File: LICENSE
Requires-Dist: psutil >=5.9.1
Requires-Dist: python-magic >=0.4.11
Requires-Dist: rel >=0.4.9.21
